LICENSE
README.md
setup.py
edgeimpulse_ota/InputLibrary.py
edgeimpulse_ota/Quantization.py
edgeimpulse_ota/TensorData.py
edgeimpulse_ota/__init__.py
edgeimpulse_ota/patch.py
edgeimpulse_ota/serve.py
edgeimpulse_ota.egg-info/PKG-INFO
edgeimpulse_ota.egg-info/SOURCES.txt
edgeimpulse_ota.egg-info/dependency_links.txt
edgeimpulse_ota.egg-info/requires.txt
edgeimpulse_ota.egg-info/top_level.txt
edgeimpulse_ota/templates/ota.cpp.jinja
edgeimpulse_ota/templates/ota.h.jinja