Metadata-Version: 2.1
Name: edgeimpulse-ota
Version: 1.0.3
Summary: OTA updates for Edge Impulse models
Home-page: https://github.com/eloquentarduino/python-edgeimpulse-ota
Author: Simone Salerno
Author-email: support@eloquentarduino.com
License: MIT
Keywords: ML,Edge AI
License-File: LICENSE
